.gitignore
.travis.yml
MANIFEST.in
README.rst
bootstrap.py
buildout.cfg
collective.etherpad-configure.zcml
settings.json.template
setup.py
travis.cfg
collective/__init__.py
collective.etherpad.egg-info/PKG-INFO
collective.etherpad.egg-info/SOURCES.txt
collective.etherpad.egg-info/dependency_links.txt
collective.etherpad.egg-info/entry_points.txt
collective.etherpad.egg-info/namespace_packages.txt
collective.etherpad.egg-info/not-zip-safe
collective.etherpad.egg-info/requires.txt
collective.etherpad.egg-info/top_level.txt
collective/etherpad/__init__.py
collective/etherpad/api.py
collective/etherpad/archetypes.py
collective/etherpad/configure.zcml
collective/etherpad/dexterity.py
collective/etherpad/etherpad_view.pt
collective/etherpad/etherpad_view.py
collective/etherpad/layer.py
collective/etherpad/rebuild_i18n.sh
collective/etherpad/settings.py
collective/etherpad/testing.py
collective/etherpad/upgrades.py
collective/etherpad/upgrades.zcml
collective/etherpad/Extensions/Install.py
collective/etherpad/locales/collective.etherpad.pot
collective/etherpad/locales/plone.pot
collective/etherpad/locales/en/LC_MESSAGES/collective.etherpad.mo
collective/etherpad/locales/en/LC_MESSAGES/collective.etherpad.po
collective/etherpad/locales/fr/LC_MESSAGES/collective.etherpad.mo
collective/etherpad/locales/fr/LC_MESSAGES/collective.etherpad.po
collective/etherpad/locales/fr/LC_MESSAGES/plone.mo
collective/etherpad/locales/fr/LC_MESSAGES/plone.po
collective/etherpad/profiles/default/browserlayer.xml
collective/etherpad/profiles/default/metadata.xml
collective/etherpad/profiles/default/registry.xml
collective/etherpad/profiles/default/types.xml
collective/etherpad/profiles/default/types/Document.xml
collective/etherpad/profiles/default/types/Event.xml
collective/etherpad/profiles/default/types/News_Item.xml
collective/etherpad/profiles/default/types/Topic.xml
collective/etherpad/tests/__init__.py
collective/etherpad/tests/base.py
collective/etherpad/tests/fake.py
collective/etherpad/tests/test_api.py
collective/etherpad/tests/test_archetypes.py
collective/etherpad/tests/test_dexterity.py
collective/etherpad/tests/test_setup.py
docs/HISTORY.txt